qibolab/__init__.py
qibolab/_core/__init__.py
qibolab/_core/backends.py
qibolab/_core/compilers/__init__.py
qibolab/_core/compilers/compiler.py
qibolab/_core/compilers/default.py
qibolab/_core/components/__init__.py
qibolab/_core/components/channels.py
qibolab/_core/components/configs.py
qibolab/_core/components/filters.py
qibolab/_core/dummy/__init__.py
qibolab/_core/dummy/parameters.json
qibolab/_core/dummy/platform.py
qibolab/_core/execution_parameters.py
qibolab/_core/identifier.py
qibolab/_core/instruments/__init__.py
qibolab/_core/instruments/abstract.py
qibolab/_core/instruments/bluefors.py
qibolab/_core/instruments/dummy.py
qibolab/_core/instruments/emulator/__init__.py
qibolab/_core/instruments/emulator/emulator.py
qibolab/_core/instruments/emulator/engine/__init__.py
qibolab/_core/instruments/emulator/engine/abstract.py
qibolab/_core/instruments/emulator/engine/qutip.py
qibolab/_core/instruments/emulator/hamiltonians.py
qibolab/_core/instruments/emulator/results.py
qibolab/_core/instruments/erasynth.py
qibolab/_core/instruments/keysight/__init__.py
qibolab/_core/instruments/keysight/components/__init__.py
qibolab/_core/instruments/keysight/components/configs.py
qibolab/_core/instruments/keysight/pulse.py
qibolab/_core/instruments/keysight/qcs.py
qibolab/_core/instruments/keysight/results.py
qibolab/_core/instruments/keysight/sweep.py
qibolab/_core/instruments/oscillator.py
qibolab/_core/instruments/qblox/__init__.py
qibolab/_core/instruments/qblox/cluster.py
qibolab/_core/instruments/qblox/config/__init__.py
qibolab/_core/instruments/qblox/config/module.py
qibolab/_core/instruments/qblox/config/port.py
qibolab/_core/instruments/qblox/config/sequencer.py
qibolab/_core/instruments/qblox/identifiers.py
qibolab/_core/instruments/qblox/log.py
qibolab/_core/instruments/qblox/mock/__init__.py
qibolab/_core/instruments/qblox/mock/cluster.py
qibolab/_core/instruments/qblox/mock/hook.py
qibolab/_core/instruments/qblox/platform.py
qibolab-0.2.11.dist-info/METADATA
qibolab-0.2.11.dist-info/WHEEL
qibolab-0.2.11.dist-info/licenses/LICENSE
qibolab-0.2.11.dist-info/RECORD
