Metadata-Version: 2.4
Name: qibolab
Version: 0.2.11
Summary: Quantum hardware module and drivers for Qibo
License: Apache-2.0
License-File: LICENSE
Author: The Qibo team
Requires-Python: >=3.10,<3.14
Classifier: License :: OSI Approved :: Apache Software License
Classifier: Programming Language :: Python :: 3
Classifier: Programming Language :: Python :: 3.10
Classifier: Programming Language :: Python :: 3.11
Classifier: Programming Language :: Python :: 3.12
Classifier: Programming Language :: Python :: 3.13
Classifier: Topic :: Scientific/Engineering :: Physics
Provides-Extra: backend
Provides-Extra: emulator
Provides-Extra: qrng
Requires-Dist: numpy (>=1.26.0,<3)
Requires-Dist: pydantic (>=2.4.0,<3.0.0)
Requires-Dist: pyserial (>=3.5,<4.0) ; extra == "qrng"
Requires-Dist: qibo (>=0.2.16,<0.3.0) ; extra == "backend"
Requires-Dist: qutip (>=5.0.2,<6.0.0) ; extra == "emulator"
Requires-Dist: scipy (>=1.13.0,<2.0.0)
Project-URL: Documentation, https://qibo.science/docs/qibolab/stable
Project-URL: Homepage, https://qibo.science/
Project-URL: Repository, https://github.com/qiboteam/qibolab/
